{
  "url": "https://www.bk.com/",
  "extractedAt": "2025-12-02T23:39:47.497Z",
  "logo": {
    "source": "img",
    "url": "https://cdn.cookielaw.org/logos/static/ot_company_logo.png",
    "width": 600,
    "height": 106,
    "alt": "Burger King Logo",
    "safeZone": {
      "top": 0,
      "right": 0,
      "bottom": 0,
      "left": 0
    }
  },
  "favicons": [
    {
      "type": "icon",
      "url": "https://burgerking.com/favicon.ico",
      "sizes": null
    }
  ],
  "colors": {
    "semantic": {},
    "palette": [
      {
        "color": "rgb(0, 0, 0)",
        "normalized": "#000000",
        "count": 485,
        "confidence": "high",
        "sources": [
          "css-g5y9jx",
          "ot-sdk-twelve",
          "cookie-settings-btn-only"
        ]
      },
      {
        "color": "rgb(0, 0, 238)",
        "normalized": "#0000ee",
        "count": 172,
        "confidence": "high",
        "sources": []
      },
      {
        "color": "rgb(62, 32, 33)",
        "normalized": "#3e2021",
        "count": 57,
        "confidence": "high",
        "sources": [
          "privacy-notice-link",
          "ot-cat-header",
          "ot-link-btn"
        ]
      },
      {
        "color": "rgb(80, 35, 20)",
        "normalized": "#502314",
        "count": 49,
        "confidence": "high",
        "sources": [
          "css-g5y9jx"
        ]
      },
      {
        "color": "rgb(85, 85, 85)",
        "normalized": "#555555",
        "count": 31,
        "confidence": "high",
        "sources": [
          "onetrust-close-btn-handler",
          "ot-close-icon",
          "ot-link-btn"
        ]
      },
      {
        "color": "rgb(248, 241, 231)",
        "normalized": "#f8f1e7",
        "count": 17,
        "confidence": "medium",
        "sources": []
      },
      {
        "color": "rgb(215, 35, 0)",
        "normalized": "#d72300",
        "count": 10,
        "confidence": "high",
        "sources": [
          "ot-pc-refuse-all-handler",
          "save-preference-btn-handler"
        ]
      },
      {
        "color": "rgb(216, 216, 216)",
        "normalized": "#d8d8d8",
        "count": 9,
        "confidence": "medium",
        "sources": []
      },
      {
        "color": "rgb(39, 69, 92)",
        "normalized": "#27455c",
        "count": 8,
        "confidence": "medium",
        "sources": []
      },
      {
        "color": "rgb(255, 255, 255)",
        "normalized": "#ffffff",
        "count": 7,
        "confidence": "medium",
        "sources": []
      },
      {
        "color": "rgb(56, 96, 190)",
        "normalized": "#3860be",
        "count": 6,
        "confidence": "high",
        "sources": []
      },
      {
        "color": "rgb(16, 16, 16)",
        "normalized": "#101010",
        "count": 1,
        "confidence": "medium",
        "sources": [
          "hover/focus"
        ]
      },
      {
        "color": "rgba(0, 0, 0, 0.04)",
        "normalized": "#000000",
        "count": 1,
        "confidence": "medium",
        "sources": [
          "hover/focus"
        ]
      },
      {
        "color": "rgb(167, 27, 0)",
        "normalized": "#a71b00",
        "count": 1,
        "confidence": "medium",
        "sources": [
          "hover/focus"
        ]
      },
      {
        "color": "rgba(80, 35, 20, 0.15)",
        "normalized": "#502314",
        "count": 1,
        "confidence": "medium",
        "sources": [
          "hover/focus"
        ]
      }
    ],
    "cssVariables": {}
  },
  "typography": {
    "styles": [
      {
        "context": "heading-1",
        "family": "Flame-Bold",
        "fallbacks": null,
        "size": "60px (3.75rem)",
        "weight": 400,
        "lineHeight": "1.13",
        "spacing": null,
        "transform": null
      },
      {
        "context": "heading-1",
        "family": "Flame-Regular",
        "fallbacks": null,
        "size": "24px (1.50rem)",
        "weight": 400,
        "lineHeight": "1.17",
        "spacing": null,
        "transform": null
      },
      {
        "context": "heading-1",
        "family": "Times New Roman",
        "fallbacks": null,
        "size": "24px (1.50rem)",
        "weight": 400,
        "lineHeight": null,
        "spacing": null,
        "transform": null
      },
      {
        "context": "link",
        "family": "Times New Roman",
        "fallbacks": null,
        "size": "16px (1.00rem)",
        "weight": 400,
        "lineHeight": null,
        "spacing": null,
        "transform": null
      },
      {
        "context": "heading-1",
        "family": "Flame Sans",
        "fallbacks": "Helvetica Neue, Helvetica, Arial, Verdana",
        "size": "16px (1.00rem)",
        "weight": 400,
        "lineHeight": null,
        "spacing": null,
        "transform": null
      },
      {
        "context": "heading-1",
        "family": "Times New Roman",
        "fallbacks": null,
        "size": "16px (1.00rem)",
        "weight": 700,
        "lineHeight": "1.50",
        "spacing": null,
        "transform": null
      },
      {
        "context": "heading-1",
        "family": "Times New Roman",
        "fallbacks": null,
        "size": "16px (1.00rem)",
        "weight": 400,
        "lineHeight": null,
        "spacing": null,
        "transform": null
      },
      {
        "context": "button",
        "family": "Times New Roman",
        "fallbacks": null,
        "size": "16px (1.00rem)",
        "weight": 400,
        "lineHeight": null,
        "spacing": "0.16px",
        "transform": null
      },
      {
        "context": "button",
        "family": "Flame Sans",
        "fallbacks": "Helvetica Neue, Helvetica, Arial, Verdana",
        "size": "14.4px (0.90rem)",
        "weight": 400,
        "lineHeight": "2.64",
        "spacing": "0.144px",
        "transform": null
      },
      {
        "context": "button",
        "family": "Times New Roman",
        "fallbacks": null,
        "size": "14.4px (0.90rem)",
        "weight": 700,
        "lineHeight": "1.00",
        "spacing": "0.144px",
        "transform": null
      },
      {
        "context": "caption",
        "family": "Times New Roman",
        "fallbacks": null,
        "size": "14px (0.88rem)",
        "weight": 700,
        "lineHeight": "1.50",
        "spacing": null,
        "transform": null
      },
      {
        "context": "caption",
        "family": "Times New Roman",
        "fallbacks": null,
        "size": "14px (0.88rem)",
        "weight": 600,
        "lineHeight": "1.50",
        "spacing": null,
        "transform": null
      },
      {
        "context": "caption",
        "family": "Times New Roman",
        "fallbacks": null,
        "size": "13.6px (0.85rem)",
        "weight": 400,
        "lineHeight": null,
        "spacing": null,
        "transform": null
      },
      {
        "context": "button",
        "family": "Arial",
        "fallbacks": null,
        "size": "13.3333px (0.83rem)",
        "weight": 400,
        "lineHeight": null,
        "spacing": null,
        "transform": null
      },
      {
        "context": "link",
        "family": "Flame Sans",
        "fallbacks": "Helvetica Neue, Helvetica, Arial, Verdana",
        "size": "13.008px (0.81rem)",
        "weight": 700,
        "lineHeight": "1.50",
        "spacing": null,
        "transform": null
      },
      {
        "context": "button",
        "family": "Flame Sans",
        "fallbacks": "Helvetica Neue, Helvetica, Arial, Verdana",
        "size": "13.008px (0.81rem)",
        "weight": 600,
        "lineHeight": "1.20",
        "spacing": "0.13008px",
        "transform": null
      },
      {
        "context": "button",
        "family": "Times New Roman",
        "fallbacks": null,
        "size": "13.008px (0.81rem)",
        "weight": 400,
        "lineHeight": null,
        "spacing": "0.13008px",
        "transform": null
      },
      {
        "context": "link",
        "family": "Times New Roman",
        "fallbacks": null,
        "size": "12.992px (0.81rem)",
        "weight": 400,
        "lineHeight": "1.50",
        "spacing": null,
        "transform": null
      },
      {
        "context": "caption",
        "family": "Times New Roman",
        "fallbacks": null,
        "size": "12.992px (0.81rem)",
        "weight": 400,
        "lineHeight": "1.50",
        "spacing": null,
        "transform": null
      },
      {
        "context": "button",
        "family": "Times New Roman",
        "fallbacks": null,
        "size": "12px (0.75rem)",
        "weight": 700,
        "lineHeight": "1.00",
        "spacing": "0.96px",
        "transform": null
      },
      {
        "context": "link",
        "family": "Times New Roman",
        "fallbacks": null,
        "size": "12px (0.75rem)",
        "weight": 400,
        "lineHeight": null,
        "spacing": null,
        "transform": null
      }
    ],
    "sources": {
      "googleFonts": [],
      "adobeFonts": false,
      "variableFonts": false
    }
  },
  "spacing": {
    "scaleType": "8px",
    "commonValues": [
      {
        "px": "1px",
        "rem": "0.06rem",
        "count": 5,
        "numericValue": 1
      },
      {
        "px": "2px",
        "rem": "0.13rem",
        "count": 4,
        "numericValue": 2
      },
      {
        "px": "4px",
        "rem": "0.25rem",
        "count": 1,
        "numericValue": 4
      },
      {
        "px": "5px",
        "rem": "0.31rem",
        "count": 18,
        "numericValue": 5
      },
      {
        "px": "6px",
        "rem": "0.38rem",
        "count": 2,
        "numericValue": 6
      },
      {
        "px": "8px",
        "rem": "0.50rem",
        "count": 21,
        "numericValue": 8
      },
      {
        "px": "10px",
        "rem": "0.63rem",
        "count": 20,
        "numericValue": 10
      },
      {
        "px": "11.2px",
        "rem": "0.70rem",
        "count": 8,
        "numericValue": 11.2
      },
      {
        "px": "12px",
        "rem": "0.75rem",
        "count": 20,
        "numericValue": 12
      },
      {
        "px": "15px",
        "rem": "0.94rem",
        "count": 4,
        "numericValue": 15
      },
      {
        "px": "16px",
        "rem": "1.00rem",
        "count": 14,
        "numericValue": 16
      },
      {
        "px": "19px",
        "rem": "1.19rem",
        "count": 2,
        "numericValue": 19
      },
      {
        "px": "20px",
        "rem": "1.25rem",
        "count": 7,
        "numericValue": 20
      },
      {
        "px": "24px",
        "rem": "1.50rem",
        "count": 2,
        "numericValue": 24
      },
      {
        "px": "25px",
        "rem": "1.56rem",
        "count": 2,
        "numericValue": 25
      },
      {
        "px": "32px",
        "rem": "2.00rem",
        "count": 2,
        "numericValue": 32
      },
      {
        "px": "40px",
        "rem": "2.50rem",
        "count": 2,
        "numericValue": 40
      },
      {
        "px": "48px",
        "rem": "3.00rem",
        "count": 1,
        "numericValue": 48
      },
      {
        "px": "80px",
        "rem": "5.00rem",
        "count": 1,
        "numericValue": 80
      },
      {
        "px": "150px",
        "rem": "9.38rem",
        "count": 1,
        "numericValue": 150
      }
    ]
  },
  "borderRadius": {
    "values": [
      {
        "value": "1px",
        "count": 8,
        "confidence": "medium",
        "numericValue": 1
      },
      {
        "value": "2px",
        "count": 22,
        "confidence": "high",
        "numericValue": 2
      },
      {
        "value": "2.5px",
        "count": 2,
        "confidence": "low",
        "numericValue": 2.5
      },
      {
        "value": "3px",
        "count": 2,
        "confidence": "low",
        "numericValue": 3
      },
      {
        "value": "16px",
        "count": 2,
        "confidence": "low",
        "numericValue": 16
      },
      {
        "value": "16px 16px 0px 0px",
        "count": 2,
        "confidence": "low",
        "numericValue": 16
      },
      {
        "value": "17px",
        "count": 1,
        "confidence": "low",
        "numericValue": 17
      },
      {
        "value": "20px",
        "count": 2,
        "confidence": "low",
        "numericValue": 20
      },
      {
        "value": "50px",
        "count": 1,
        "confidence": "low",
        "numericValue": 50
      },
      {
        "value": "9999px",
        "count": 6,
        "confidence": "medium",
        "numericValue": 9999
      }
    ]
  },
  "borders": {
    "widths": [
      {
        "value": "0px 0px 1px",
        "count": 1,
        "confidence": "low",
        "numericValue": 0
      },
      {
        "value": "0px 1px 1px",
        "count": 3,
        "confidence": "low",
        "numericValue": 0
      },
      {
        "value": "1px",
        "count": 17,
        "confidence": "high",
        "numericValue": 1
      },
      {
        "value": "1px 0px 0px",
        "count": 2,
        "confidence": "low",
        "numericValue": 1
      },
      {
        "value": "2px",
        "count": 4,
        "confidence": "medium",
        "numericValue": 2
      },
      {
        "value": "12px",
        "count": 1,
        "confidence": "low",
        "numericValue": 12
      }
    ],
    "styles": [
      {
        "value": "solid",
        "count": 212,
        "confidence": "high"
      },
      {
        "value": "inset",
        "count": 4,
        "confidence": "medium"
      },
      {
        "value": "none solid solid",
        "count": 3,
        "confidence": "low"
      },
      {
        "value": "none none solid",
        "count": 1,
        "confidence": "low"
      },
      {
        "value": "solid none none",
        "count": 1,
        "confidence": "low"
      }
    ],
    "colors": [
      {
        "value": "rgb(0, 0, 0)",
        "count": 12,
        "confidence": "high"
      },
      {
        "value": "rgb(216, 216, 216)",
        "count": 9,
        "confidence": "medium"
      },
      {
        "value": "rgb(215, 35, 0)",
        "count": 5,
        "confidence": "medium"
      },
      {
        "value": "rgb(80, 35, 20)",
        "count": 3,
        "confidence": "low"
      },
      {
        "value": "rgb(255, 255, 255)",
        "count": 2,
        "confidence": "low"
      },
      {
        "value": "rgba(0, 0, 0, 0.3)",
        "count": 1,
        "confidence": "low"
      },
      {
        "value": "rgb(233, 233, 233)",
        "count": 1,
        "confidence": "low"
      },
      {
        "value": "rgb(50, 174, 136)",
        "count": 1,
        "confidence": "low"
      },
      {
        "value": "rgb(209, 209, 209)",
        "count": 1,
        "confidence": "low"
      },
      {
        "value": "rgb(187, 187, 187)",
        "count": 1,
        "confidence": "low"
      }
    ]
  },
  "shadows": [
    {
      "shadow": "rgba(0, 0, 0, 0.22) 0px 1px 2.22px 0px",
      "count": 2,
      "confidence": "low"
    },
    {
      "shadow": "rgba(0, 0, 0, 0.2) 0px 0px 18px 0px",
      "count": 1,
      "confidence": "low"
    },
    {
      "shadow": "rgb(153, 153, 153) 0px 2px 10px -3px",
      "count": 1,
      "confidence": "low"
    },
    {
      "shadow": "rgb(199, 197, 199) -3px -3px 5px -2px",
      "count": 1,
      "confidence": "low"
    },
    {
      "shadow": "rgb(199, 197, 199) 0px 0px 12px 2px",
      "count": 1,
      "confidence": "low"
    }
  ],
  "components": {
    "buttons": [
      {
        "backgroundColor": "rgba(0, 0, 0, 0)",
        "color": "rgba(0, 0, 0, 0.7)",
        "padding": "8px 16px",
        "borderRadius": "9999px",
        "border": "1px solid rgba(0, 0, 0, 0.3)",
        "fontWeight": "400",
        "fontSize": "13.3333px",
        "classes": "css-g5y9jx r-12vffkv r-1awozwy r-1niwhzg r-1crrai2",
        "confidence": "high"
      },
      {
        "backgroundColor": "rgb(167, 27, 0)",
        "color": "rgba(0, 0, 0, 0.7)",
        "padding": "8px 16px",
        "borderRadius": "9999px",
        "border": "0px solid rgb(0, 0, 0)",
        "fontWeight": "400",
        "fontSize": "13.3333px",
        "classes": "css-g5y9jx r-1otgn73 r-1awozwy r-1185ocx r-sdzlij ",
        "confidence": "high"
      },
      {
        "backgroundColor": "rgb(244, 235, 220)",
        "color": "rgb(0, 0, 0)",
        "padding": "12px 10px",
        "borderRadius": "2px",
        "border": "1px solid rgb(0, 0, 0)",
        "fontWeight": "600",
        "fontSize": "13.008px",
        "classes": "cookie-settings-btn-only",
        "confidence": "high"
      }
    ],
    "inputs": [
      {
        "type": "input",
        "border": "0px none rgb(0, 0, 0)",
        "borderRadius": "0px",
        "padding": "0px",
        "backgroundColor": "rgba(0, 0, 0, 0)",
        "focusStyles": {
          "outline": "rgb(0, 0, 0) none 0px"
        }
      },
      {
        "type": "input",
        "border": "1px solid rgb(209, 209, 209)",
        "borderRadius": "50px",
        "padding": "6px 35px 6px 15px",
        "backgroundColor": "rgb(255, 255, 255)",
        "focusStyles": {
          "outline": "rgb(0, 0, 0) none 0px"
        }
      }
    ],
    "links": [
      {
        "color": "rgb(80, 35, 20)",
        "textDecoration": "none",
        "fontWeight": "400",
        "hoverColor": null,
        "hoverDecoration": null
      },
      {
        "color": "rgb(80, 35, 20)",
        "textDecoration": "underline",
        "fontWeight": "400",
        "hoverColor": null,
        "hoverDecoration": null
      },
      {
        "color": "rgb(0, 0, 238)",
        "textDecoration": "underline",
        "fontWeight": "400",
        "hoverColor": null,
        "hoverDecoration": null
      },
      {
        "color": "rgb(248, 241, 231)",
        "textDecoration": "underline",
        "fontWeight": "400",
        "hoverColor": null,
        "hoverDecoration": null
      },
      {
        "color": "rgb(0, 0, 238)",
        "textDecoration": "none",
        "fontWeight": "400",
        "hoverColor": null,
        "hoverDecoration": null
      },
      {
        "color": "rgb(62, 32, 33)",
        "textDecoration": "underline",
        "fontWeight": "700",
        "hoverColor": null,
        "hoverDecoration": null
      },
      {
        "color": "rgb(101, 101, 101)",
        "textDecoration": "none",
        "fontWeight": "400",
        "hoverColor": null,
        "hoverDecoration": null
      }
    ]
  },
  "breakpoints": [
    {
      "px": "400px"
    },
    {
      "px": "425px"
    },
    {
      "px": "426px"
    },
    {
      "px": "476px"
    },
    {
      "px": "480px"
    },
    {
      "px": "530px"
    },
    {
      "px": "550px"
    },
    {
      "px": "600px"
    },
    {
      "px": "601px"
    },
    {
      "px": "640px"
    },
    {
      "px": "750px"
    },
    {
      "px": "768px"
    },
    {
      "px": "896px"
    },
    {
      "px": "992px"
    }
  ],
  "iconSystem": [],
  "frameworks": []
}